[
  { "cod":"ac", "nome":"Acre"                },
  { "cod":"al", "nome":"Alagoas"             },
  { "cod":"ap", "nome":"Amapá"               },
  { "cod":"am", "nome":"Amazonas"            },
  { "cod":"ba", "nome":"Bahia"               },
  { "cod":"ce", "nome":"Ceará"               },
  { "cod":"df", "nome":"Distrito Federal"    },
  { "cod":"es", "nome":"Espírito Santo"      },
  { "cod":"go", "nome":"Goiás"               },
  { "cod":"ma", "nome":"Maranhão"            },
  { "cod":"mt", "nome":"Mato Grosso"         },
  { "cod":"ms", "nome":"Mato Grosso do Sul"  },
  { "cod":"mg", "nome":"Minas Gerais"        },
  { "cod":"pa", "nome":"Pará"                },
  { "cod":"pb", "nome":"Paraíba"             },
  { "cod":"pr", "nome":"Paraná"              },
  { "cod":"pe", "nome":"Pernambuco"          },
  { "cod":"pi", "nome":"Piauí"               },
  { "cod":"rr", "nome":"Roraima"             },
  { "cod":"ro", "nome":"Rondônia"            },
  { "cod":"rj", "nome":"Rio de Janeiro"      },
  { "cod":"rn", "nome":"Rio Grande do Norte" },
  { "cod":"rs", "nome":"Rio Grande do Sul"   },
  { "cod":"sc", "nome":"Santa Catarina"      },
  { "cod":"sp", "nome":"São Paulo"           },
  { "cod":"se", "nome":"Sergipe"             },
  { "cod":"to", "nome":"Tocantins"           }
]