[
  {"key":"alvaraes", "value":"Alvarães"},
  {"key":"amatura", "value":"Amaturá"},
  {"key":"anama", "value":"Anamã"},
  {"key":"anori", "value":"Anori"},
  {"key":"apui", "value":"Apuí"},
  {"key":"atalaia do norte", "value":"Atalaia do Norte"},
  {"key":"autazes", "value":"Autazes"},
  {"key":"barcelos", "value":"Barcelos"},
  {"key":"barreirinha", "value":"Barreirinha"},
  {"key":"benjamin constant", "value":"Benjamin Constant"},
  {"key":"beruri", "value":"Beruri"},
  {"key":"boa vista do ramos", "value":"Boa Vista do Ramos"},
  {"key":"boca do acre", "value":"Boca do Acre"},
  {"key":"borba", "value":"Borba"},
  {"key":"caapiranga", "value":"Caapiranga"},
  {"key":"canutama", "value":"Canutama"},
  {"key":"carauari", "value":"Carauari"},
  {"key":"careiro", "value":"Careiro"},
  {"key":"careiro da varzea", "value":"Careiro da Várzea"},
  {"key":"coari", "value":"Coari"},
  {"key":"codajas", "value":"Codajás"},
  {"key":"eirunepe", "value":"Eirunepé"},
  {"key":"envira", "value":"Envira"},
  {"key":"fonte boa", "value":"Fonte Boa"},
  {"key":"guajara", "value":"Guajará"},
  {"key":"humaita", "value":"Humaitá"},
  {"key":"ipixuna", "value":"Ipixuna"},
  {"key":"iranduba", "value":"Iranduba"},
  {"key":"itacoatiara", "value":"Itacoatiara"},
  {"key":"itamarati", "value":"Itamarati"},
  {"key":"itapiranga", "value":"Itapiranga"},
  {"key":"japura", "value":"Japurá"},
  {"key":"jurua", "value":"Juruá"},
  {"key":"jutai", "value":"Jutaí"},
  {"key":"labrea", "value":"Lábrea"},
  {"key":"manacapuru", "value":"Manacapuru"},
  {"key":"manaquiri", "value":"Manaquiri"},
  {"key":"manaus", "value":"Manaus"},
  {"key":"manicore", "value":"Manicoré"},
  {"key":"maraa", "value":"Maraã"},
  {"key":"maues", "value":"Maués"},
  {"key":"nhamunda", "value":"Nhamundá"},
  {"key":"nova olinda do norte", "value":"Nova Olinda do Norte"},
  {"key":"novo airao", "value":"Novo Airão"},
  {"key":"novo aripuana", "value":"Novo Aripuanã"},
  {"key":"parintins", "value":"Parintins"},
  {"key":"pauini", "value":"Pauini"},
  {"key":"presidente figueiredo", "value":"Presidente Figueiredo"},
  {"key":"rio preto da eva", "value":"Rio Preto da Eva"},
  {"key":"santa isabel do rio negro", "value":"Santa Isabel do Rio Negro"},
  {"key":"santo antonio do ica", "value":"Santo Antônio do Içá"},
  {"key":"sao gabriel da cachoeira", "value":"São Gabriel da Cachoeira"},
  {"key":"sao paulo de olivenca", "value":"São Paulo de Olivença"},
  {"key":"sao sebastiao do uatuma", "value":"São Sebastião do Uatumã"},
  {"key":"silves", "value":"Silves"},
  {"key":"tabatinga", "value":"Tabatinga"},
  {"key":"tapaua", "value":"Tapauá"},
  {"key":"tefe", "value":"Tefé"},
  {"key":"tonantins", "value":"Tonantins"},
  {"key":"uarini", "value":"Uarini"},
  {"key":"urucara", "value":"Urucará"},
  {"key":"urucurituba", "value":"Urucurituba"}
]