[
  {"key":"amapa", "value":"Amapá"},
  {"key":"calcoene", "value":"Calçoene"},
  {"key":"cutias", "value":"Cutias"},
  {"key":"ferreira gomes", "value":"Ferreira Gomes"},
  {"key":"itaubal", "value":"Itaubal"},
  {"key":"laranjal do jari", "value":"Laranjal do Jari"},
  {"key":"macapa", "value":"Macapá"},
  {"key":"mazagao", "value":"Mazagão"},
  {"key":"oiapoque", "value":"Oiapoque"},
  {"key":"pedra branca do amapari", "value":"Pedra Branca do Amapari"},
  {"key":"porto grande", "value":"Porto Grande"},
  {"key":"pracuuba", "value":"Pracuúba"},
  {"key":"santana", "value":"Santana"},
  {"key":"serra do navio", "value":"Serra do Navio"},
  {"key":"tartarugalzinho", "value":"Tartarugalzinho"},
  {"key":"vitoria do jari", "value":"Vitória do Jari"}
]